utilki/__init__.py
utilki/cli.py
utilki/kv.py
utilki/log_utils.py
utilki/py.typed
utilki/task_mixin.py
utilki-0.13.0.dist-info/METADATA
utilki-0.13.0.dist-info/WHEEL
utilki-0.13.0.dist-info/entry_points.txt
utilki-0.13.0.dist-info/RECORD
