Metadata-Version: 2.1
Name: utilki
Version: 0.13.0
Summary: A collection of useful utilities
Author: Khaidar Bikmaev
Author-email: khaidar@bikmaev.com
Requires-Python: >=3.10
Classifier: Programming Language :: Python :: 3
Classifier: Programming Language :: Python :: 3.10
Classifier: Programming Language :: Python :: 3.11
Classifier: Programming Language :: Python :: 3.12
Requires-Dist: click (>=8.1.3,<9.0.0)
Requires-Dist: pandas (>=1.3.3)
Requires-Dist: pydantic (>=2.5.0)
Requires-Dist: result (>=0.14.0,<0.15.0)
